bsearch.py
bsearch/__init__.py
bsearch/bsearch.py
bsearch-0.0.4.dist-info/METADATA
bsearch-0.0.4.dist-info/WHEEL
bsearch-0.0.4.dist-info/top_level.txt
bsearch-0.0.4.dist-info/RECORD
