Metadata-Version: 2.1
Name: bsearch
Version: 0.0.4
Summary: Binary search - bisect_left and bisect_right with more flexible comparison
Home-page: https://github.com/domsleee/bsearch
Author: Dominic Slee
Author-email: domslee1@gmail.com
License: BSD
Platform: UNKNOWN
Classifier: Programming Language :: Python :: 2
Classifier: Programming Language :: Python :: 3
